{
  "Workflows": [
    {
      "Path": null,
      "SortBy": 0,
      "VariablesSectionElementsOrder": [],
      "ArgumentsSectionElementsOrder": null,
      "ConstantsSectionElementsOrder": [],
      "AddedNamespaces": null
    },
    {
      "Path": "Framework/InitAllSettings.xaml",
      "SortBy": 0,
      "VariablesSectionElementsOrder": [
        "Settings&Sequence_2",
        "Constants&Sequence_2"
      ],
      "ArgumentsSectionElementsOrder": [
        "in_Remoto",
        "out_Config"
      ],
      "ConstantsSectionElementsOrder": [],
      "AddedNamespaces": null
    },
    {
      "Path": "Framework/InitAllApplications.xaml",
      "SortBy": 0,
      "VariablesSectionElementsOrder": [],
      "ArgumentsSectionElementsOrder": [
        "io_Config"
      ],
      "ConstantsSectionElementsOrder": [],
      "AddedNamespaces": null
    },
    {
      "Path": "Framework/GetTransactionData.xaml",
      "SortBy": 0,
      "VariablesSectionElementsOrder": [
        "Query&Sequence_9"
      ],
      "ArgumentsSectionElementsOrder": [
        "io_Config",
        "in_TransactionNumber",
        "out_TransactionItem",
        "out_TransactionID",
        "out_TransactionName",
        "io_TransactionData"
      ],
      "ConstantsSectionElementsOrder": [],
      "AddedNamespaces": null
    },
    {
      "Path": "Main.xaml",
      "SortBy": 0,
      "VariablesSectionElementsOrder": [
        "TransactionItem&StateMachine_1",
        "SystemException&StateMachine_1",
        "BusinessException&StateMachine_1",
        "TransactionNumber&StateMachine_1",
        "Config&StateMachine_1",
        "RetryNumber&StateMachine_1",
        "TransactionField2&StateMachine_1",
        "TransactionName&StateMachine_1",
        "TransactionID&StateMachine_1",
        "TransactionData&StateMachine_1",
        "ConsecutiveSystemExceptions&StateMachine_1",
        "ShouldStop&Sequence_25"
      ],
      "ArgumentsSectionElementsOrder": [
        "in_Remoto"
      ],
      "ConstantsSectionElementsOrder": [],
      "AddedNamespaces": null
    },
    {
      "Path": "Framework/SetTransactionStatus.xaml",
      "SortBy": 0,
      "VariablesSectionElementsOrder": [
        "QueueRetry&Sequence_17",
        "ScreenshotPath&Sequence_17"
      ],
      "ArgumentsSectionElementsOrder": [
        "in_BusinessException",
        "in_TransactionID",
        "in_SystemException",
        "in_Config",
        "in_TransactionItem",
        "io_RetryNumber",
        "io_TransactionNumber",
        "io_ConsecutiveSystemExceptions",
        "in_TransactionNome"
      ],
      "ConstantsSectionElementsOrder": [],
      "AddedNamespaces": null
    },
    {
      "Path": "Process.xaml",
      "SortBy": 0,
      "VariablesSectionElementsOrder": [],
      "ArgumentsSectionElementsOrder": [
        "io_Config",
        "io_TransactionItem"
      ],
      "ConstantsSectionElementsOrder": [],
      "AddedNamespaces": null
    },
    {
      "Path": "Form/Config/Form Config.xaml",
      "SortBy": 0,
      "VariablesSectionElementsOrder": [
        "width&Sequence_1",
        "heigth&Sequence_1",
        "posX&Sequence_1",
        "posY&Sequence_1",
        "formName&Sequence_1",
        "parametro&Sequence_1",
        "var&Sequence_1",
        "periodo&Sequence_1",
        "perfil&Sequence_1",
        "dt_perfil&Sequence_1",
        "JsonObject&Sequence_1"
      ],
      "ArgumentsSectionElementsOrder": [
        "io_Config"
      ],
      "ConstantsSectionElementsOrder": [],
      "AddedNamespaces": null
    }
  ]
}